ChromeExploit/__init__.py
ChromeExploit/core.py
ChromeExploit-1.0.1.dist-info/LICENSE
ChromeExploit-1.0.1.dist-info/METADATA
ChromeExploit-1.0.1.dist-info/WHEEL
ChromeExploit-1.0.1.dist-info/top_level.txt
ChromeExploit-1.0.1.dist-info/RECORD
